LICENSE
MANIFEST.in
README.md
setup.py
django_google_tag_manager.egg-info/PKG-INFO
django_google_tag_manager.egg-info/SOURCES.txt
django_google_tag_manager.egg-info/dependency_links.txt
django_google_tag_manager.egg-info/top_level.txt
gtm/__init__.py
gtm/templates/gtm/gtm.html
gtm/templates/gtm/gtm_body.html
gtm/templates/gtm/gtm_head.html
gtm/templatetags/__init__.py
gtm/templatetags/gtm_tags.py