Metadata-Version: 1.1
Name: django-google-tag-manager
Version: 0.0.5
Summary: Easily include your Google Tag Manager tag in your django site
Home-page: https://github.com/Lacrymology/django-google-tag-manager
Author: Tomas Neme
Author-email: lacrymology@gmail.com
License: MIT
Keywords: django generic-views
Platform: UNKNOWN
Classifier: Development Status :: 3 - Alpha
Classifier: Topic :: Utilities
Classifier: License :: OSI Approved :: MIT License
